django_privacy_killer-0.3.0.dist-info/DESCRIPTION.rst
django_privacy_killer-0.3.0.dist-info/METADATA
django_privacy_killer-0.3.0.dist-info/RECORD
django_privacy_killer-0.3.0.dist-info/WHEEL
django_privacy_killer-0.3.0.dist-info/metadata.json
django_privacy_killer-0.3.0.dist-info/top_level.txt
privacy_killer/__init__.py
privacy_killer/templates/privacy_killer/facebook_pixel_head.html
privacy_killer/templates/privacy_killer/google_analytics_head.html
privacy_killer/templates/privacy_killer/google_tag_manager_body.html
privacy_killer/templates/privacy_killer/google_tag_manager_head.html
privacy_killer/templatetags/__init__.py
privacy_killer/templatetags/privacy_killer.py
